LICENSE
README.md
setup.py
CVE_2024_0195.egg-info/PKG-INFO
CVE_2024_0195.egg-info/SOURCES.txt
CVE_2024_0195.egg-info/dependency_links.txt
CVE_2024_0195.egg-info/entry_points.txt
CVE_2024_0195.egg-info/requires.txt
CVE_2024_0195.egg-info/top_level.txt
cve20240195/main.py
cve20240195/includes/__init__.py
cve20240195/includes/bot.py
cve20240195/includes/filereader.py
cve20240195/includes/scan.py
cve20240195/includes/writefile.py
cve20240195/utils/__init__.py
cve20240195/utils/configure.py
cve20240195/utils/const.py
cve20240195/utils/helpers.py
cve20240195/utils/status.py